einmesh/__init__.py
einmesh/_backends.py
einmesh/_einmesher.py
einmesh/_exceptions.py
einmesh/_operators.py
einmesh/_parser.py
einmesh/jax.py
einmesh/numpy.py
einmesh/spaces.py
einmesh/torch.py
einmesh/types.py
einmesh-0.1.2.dist-info/METADATA
einmesh-0.1.2.dist-info/WHEEL
einmesh-0.1.2.dist-info/licenses/LICENSE
einmesh-0.1.2.dist-info/RECORD
