Metadata-Version: 2.4
Name: einmesh
Version: 0.1.2
Summary: einops style multi dimensional meshgrids
Project-URL: Homepage, https://einmesh.xyz
Project-URL: Repository, https://github.com/niels-skovgaard-jensen/einmesh
Project-URL: Documentation, https://einmesh.xyz
Author-email: Niels Skovgaard Jensen <niels@skovgaardjensen.io>
License-File: LICENSE
Keywords: einmesh,einops,jax,meshgrid,numpy,python,torch
Classifier: Intended Audience :: Developers
Classifier: Programming Language :: Python
Classifier: Programming Language :: Python :: 3
Classifier: Programming Language :: Python :: 3.10
Classifier: Programming Language :: Python :: 3.11
Classifier: Programming Language :: Python :: 3.12
Classifier: Programming Language :: Python :: 3.13
Classifier: Topic :: Software Development :: Libraries :: Python Modules
Requires-Python: <4.0,>=3.10
Requires-Dist: einmesh
Requires-Dist: einops>=0.7.0
